rotate_pcd/__init__.py
rotate_pcd/core.py
rotate_pcd-0.1.0.dist-info/METADATA
rotate_pcd-0.1.0.dist-info/WHEEL
rotate_pcd-0.1.0.dist-info/top_level.txt
rotate_pcd-0.1.0.dist-info/RECORD
